{
  "repository": {
    "pullRequests": {
      "edges": [
        {
          "node": {
            "state": "MERGED",
            "mergedAt": "2024-03-23T10:59:29Z",
            "title": "Add maximum V0 decay radius cut",
            "number": 5299,
            "author": {
              "login": "romainschotter"
            },
            "files": {
              "edges": [
                {
                  "node": {
                    "path": "PWGLF/Tasks/Strangeness/derivedlambdakzeroanalysis.cxx"
                  }
                }
              ]
            }
          }
        },
        {
          "node": {
            "state": "MERGED",
            "mergedAt": "2024-03-23T00:47:05Z",
            "title": "Add trd information",
            "number": 5300,
            "author": {
              "login": "fmazzasc"
            },
            "files": {
              "edges": [
                {
                  "node": {
                    "path": "PWGLF/TableProducer/nucleiSpectra.cxx"
                  }
                }
              ]
            }
          }
        },
        {
          "node": {
            "state": "MERGED",
            "mergedAt": "2024-03-23T01:16:49Z",
            "title": "[PWGJE]: Jet Fragmentation: Added more histograms for matched V0s",
            "number": 5301,
            "author": {
              "login": "GijsvWeelden"
            },
            "files": {
              "edges": [
                {
                  "node": {
                    "path": "PWGJE/Tasks/jetfragmentation.cxx"
                  }
                }
              ]
            }
          }
        },
        {
          "node": {
            "state": "MERGED",
            "mergedAt": "2024-03-23T01:40:08Z",
            "title": "PWG-LF: Add daughter track IU position and daughter track parameters at MC vertex to kfStrangenessStudy task",
            "number": 5302,
            "author": {
              "login": "creetz16"
            },
            "files": {
              "edges": [
                {
                  "node": {
                    "path": "PWGLF/DataModel/kfStrangenessStudy.h"
                  }
                },
                {
                  "node": {
                    "path": "PWGLF/Tasks/QC/kfStrangenessStudy.cxx"
                  }
                }
              ]
            }
          }
        },
        {
          "node": {
            "state": "MERGED",
            "mergedAt": "2024-03-23T04:44:56Z",
            "title": "PWGJE : Fixing a bug with fulljettrigger bit size",
            "number": 5303,
            "author": {
              "login": "nzardosh"
            },
            "files": {
              "edges": [
                {
                  "node": {
                    "path": "PWGJE/Core/JetDerivedDataUtilities.h"
                  }
                },
                {
                  "node": {
                    "path": "PWGJE/DataModel/JetReducedData.h"
                  }
                }
              ]
            }
          }
        },
        {
          "node": {
            "state": "CLOSED",
            "mergedAt": null,
            "title": "PWGCF: Update MeanPtFlucIdentified.cxx",
            "number": 5304,
            "author": {
              "login": "TGahlaut1"
            },
            "files": {
              "edges": [
                {
                  "node": {
                    "path": "PWGCF/EbyEFluctuations/Tasks/MeanPtFlucIdentified.cxx"
                  }
                }
              ]
            }
          }
        },
        {
          "node": {
            "state": "MERGED",
            "mergedAt": "2024-03-23T05:14:50Z",
            "title": "[PWGLF] LightNucleiTask - Fix minor issues and optimise memory",
            "number": 5305,
            "author": {
              "login": "giovannimalfattore"
            },
            "files": {
              "edges": [
                {
                  "node": {
                    "path": "PWGLF/Tasks/Nuspex/LFNucleiBATask.cxx"
                  }
                }
              ]
            }
          }
        },
        {
          "node": {
            "state": "CLOSED",
            "mergedAt": null,
            "title": "PWFCF: Update MeanPtFlucIdentified.cxx",
            "number": 5306,
            "author": {
              "login": "TGahlaut1"
            },
            "files": {
              "edges": [
                {
                  "node": {
                    "path": "PWGCF/EbyEFluctuations/Tasks/MeanPtFlucIdentified.cxx"
                  }
                }
              ]
            }
          }
        },
        {
          "node": {
            "state": "MERGED",
            "mergedAt": "2024-03-23T19:28:45Z",
            "title": "PWGCF: Update MeanPtFlucIdentified.cxx",
            "number": 5307,
            "author": {
              "login": "TGahlaut1"
            },
            "files": {
              "edges": [
                {
                  "node": {
                    "path": "PWGCF/EbyEFluctuations/Tasks/MeanPtFlucIdentified.cxx"
                  }
                }
              ]
            }
          }
        },
        {
          "node": {
            "state": "MERGED",
            "mergedAt": "2024-03-23T06:12:37Z",
            "title": "PWGCF: FemtoUniverse -- Removal of doubled configurables, adding configurable for radius for delta eta delta phi*, update of contact info",
            "number": 5308,
            "author": {
              "login": "zchochul"
            },
            "files": {
              "edges": [
                {
                  "node": {
                    "path": "PWGCF/FemtoUniverse/Core/FemtoUniverseAngularContainer.h"
                  }
                },
                {
                  "node": {
                    "path": "PWGCF/FemtoUniverse/Core/FemtoUniverseCollisionSelection.h"
                  }
                },
                {
                  "node": {
                    "path": "PWGCF/FemtoUniverse/Core/FemtoUniverseContainer.h"
                  }
                },
                {
                  "node": {
                    "path": "PWGCF/FemtoUniverse/Core/FemtoUniverseCutculator.h"
                  }
                },
                {
                  "node": {
                    "path": "PWGCF/FemtoUniverse/Core/FemtoUniverseDetaDphiStar.h"
                  }
                },
                {
                  "node": {
                    "path": "PWGCF/FemtoUniverse/Core/FemtoUniverseEventHisto.h"
                  }
                },
                {
                  "node": {
                    "path": "PWGCF/FemtoUniverse/Core/FemtoUniverseFemtoContainer.h"
                  }
                },
                {
                  "node": {
                    "path": "PWGCF/FemtoUniverse/Core/FemtoUniverseMath.h"
                  }
                },
                {
                  "node": {
                    "path": "PWGCF/FemtoUniverse/Core/FemtoUniverseObjectSelection.h"
                  }
                },
                {
                  "node": {
                    "path": "PWGCF/FemtoUniverse/Core/FemtoUniversePairCleaner.h"
                  }
                },
                {
                  "node": {
                    "path": "PWGCF/FemtoUniverse/Core/FemtoUniverseParticleHisto.h"
                  }
                },
                {
                  "node": {
                    "path": "PWGCF/FemtoUniverse/Core/FemtoUniversePhiSelection.h"
                  }
                },
                {
                  "node": {
                    "path": "PWGCF/FemtoUniverse/Core/FemtoUniverseSelection.h"
                  }
                },
                {
                  "node": {
                    "path": "PWGCF/FemtoUniverse/Core/FemtoUniverseTrackSelection.h"
                  }
                },
                {
                  "node": {
                    "path": "PWGCF/FemtoUniverse/Core/FemtoUniverseV0Selection.h"
                  }
                },
                {
                  "node": {
                    "path": "PWGCF/FemtoUniverse/Core/FemtoUtils.h"
                  }
                },
                {
                  "node": {
                    "path": "PWGCF/FemtoUniverse/TableProducer/femtoUniverseProducerMCTruthTask.cxx"
                  }
                },
                {
                  "node": {
                    "path": "PWGCF/FemtoUniverse/TableProducer/femtoUniverseProducerReducedTask.cxx"
                  }
                },
                {
                  "node": {
                    "path": "PWGCF/FemtoUniverse/TableProducer/femtoUniverseProducerTask.cxx"
                  }
                },
                {
                  "node": {
                    "path": "PWGCF/FemtoUniverse/TableProducer/femtoUniverseProducerTaskV0Only.cxx"
                  }
                },
                {
                  "node": {
                    "path": "PWGCF/FemtoUniverse/Tasks/femtoUniverseCutCulator.cxx"
                  }
                },
                {
                  "node": {
                    "path": "PWGCF/FemtoUniverse/Tasks/femtoUniverseDebugTrack.cxx"
                  }
                },
                {
                  "node": {
                    "path": "PWGCF/FemtoUniverse/Tasks/femtoUniverseDebugV0.cxx"
                  }
                },
                {
                  "node": {
                    "path": "PWGCF/FemtoUniverse/Tasks/femtoUniverseHashTask.cxx"
                  }
                },
                {
                  "node": {
                    "path": "PWGCF/FemtoUniverse/Tasks/femtoUniversePairTaskTrackD0.cxx"
                  }
                },
                {
                  "node": {
                    "path": "PWGCF/FemtoUniverse/Tasks/femtoUniversePairTaskTrackPhi.cxx"
                  }
                },
                {
                  "node": {
                    "path": "PWGCF/FemtoUniverse/Tasks/femtoUniversePairTaskTrackTrack.cxx"
                  }
                },
                {
                  "node": {
                    "path": "PWGCF/FemtoUniverse/Tasks/femtoUniversePairTaskTrackTrack3DMultKtExtended.cxx"
                  }
                },
                {
                  "node": {
                    "path": "PWGCF/FemtoUniverse/Tasks/femtoUniversePairTaskTrackTrackExtended.cxx"
                  }
                },
                {
                  "node": {
                    "path": "PWGCF/FemtoUniverse/Tasks/femtoUniversePairTaskTrackTrackMC.cxx"
                  }
                },
                {
                  "node": {
                    "path": "PWGCF/FemtoUniverse/Tasks/femtoUniversePairTaskTrackTrackMcTruth.cxx"
                  }
                },
                {
                  "node": {
                    "path": "PWGCF/FemtoUniverse/Tasks/femtoUniversePairTaskTrackTrackMultKtExtended.cxx"
                  }
                },
                {
                  "node": {
                    "path": "PWGCF/FemtoUniverse/Tasks/femtoUniversePairTaskTrackV0Extended.cxx"
                  }
                }
              ]
            }
          }
        },
        {
          "node": {
            "state": "OPEN",
            "mergedAt": null,
            "title": "[WIP] PWGCF: EbyE Intermittency analysis",
            "number": 5309,
            "author": {
              "login": "maroozm"
            },
            "files": {
              "edges": [
                {
                  "node": {
                    "path": "PWGCF/EbyEFluctuations/Tasks/CMakeLists.txt"
                  }
                },
                {
                  "node": {
                    "path": "PWGCF/EbyEFluctuations/Tasks/nfMomentsTask.cxx"
                  }
                }
              ]
            }
          }
        },
        {
          "node": {
            "state": "CLOSED",
            "mergedAt": null,
            "title": "kstar flow code",
            "number": 5310,
            "author": {
              "login": "sarjeetagami"
            },
            "files": {
              "edges": [
                {
                  "node": {
                    "path": "PWGLF/Tasks/Resonances/kstarpbpb.cxx"
                  }
                }
              ]
            }
          }
        },
        {
          "node": {
            "state": "CLOSED",
            "mergedAt": null,
            "title": "kstar flow",
            "number": 5311,
            "author": {
              "login": "sarjeetagami"
            },
            "files": {
              "edges": [
                {
                  "node": {
                    "path": "PWGLF/Tasks/Resonances/CMakeLists.txt"
                  }
                },
                {
                  "node": {
                    "path": "PWGLF/Tasks/Resonances/kstarpbpb.cxx"
                  }
                }
              ]
            }
          }
        },
        {
          "node": {
            "state": "CLOSED",
            "mergedAt": null,
            "title": "flow kstar",
            "number": 5312,
            "author": {
              "login": "sarjeetagami"
            },
            "files": {
              "edges": [
                {
                  "node": {
                    "path": "PWGLF/Tasks/Resonances/CMakeLists.txt"
                  }
                },
                {
                  "node": {
                    "path": "PWGLF/Tasks/Resonances/kstarpbpb.cxx"
                  }
                }
              ]
            }
          }
        },
        {
          "node": {
            "state": "CLOSED",
            "mergedAt": null,
            "title": "flow kstar code",
            "number": 5313,
            "author": {
              "login": "sarjeetagami"
            },
            "files": {
              "edges": [
                {
                  "node": {
                    "path": "PWGLF/Tasks/Resonances/CMakeLists.txt"
                  }
                },
                {
                  "node": {
                    "path": "PWGLF/Tasks/Resonances/kstarpbpb.cxx"
                  }
                }
              ]
            }
          }
        },
        {
          "node": {
            "state": "CLOSED",
            "mergedAt": null,
            "title": "flow kstar",
            "number": 5314,
            "author": {
              "login": "sarjeetagami"
            },
            "files": {
              "edges": [
                {
                  "node": {
                    "path": "PWGLF/Tasks/Resonances/CMakeLists.txt"
                  }
                },
                {
                  "node": {
                    "path": "PWGLF/Tasks/Resonances/kstarpbpb.cxx"
                  }
                }
              ]
            }
          }
        },
        {
          "node": {
            "state": "MERGED",
            "mergedAt": "2024-03-23T09:39:27Z",
            "title": "PWGMM: Mult: Fix reduced table descriptions",
            "number": 5315,
            "author": {
              "login": "aalkin"
            },
            "files": {
              "edges": [
                {
                  "node": {
                    "path": "PWGMM/Mult/DataModel/ReducedTables.h"
                  }
                }
              ]
            }
          }
        },
        {
          "node": {
            "state": "CLOSED",
            "mergedAt": null,
            "title": "neutral kstar flow",
            "number": 5316,
            "author": {
              "login": "sarjeetagami"
            },
            "files": {
              "edges": [
                {
                  "node": {
                    "path": "PWGLF/Tasks/Resonances/CMakeLists.txt"
                  }
                },
                {
                  "node": {
                    "path": "PWGLF/Tasks/Resonances/kstarpbpb.cxx"
                  }
                }
              ]
            }
          }
        },
        {
          "node": {
            "state": "MERGED",
            "mergedAt": "2024-03-23T10:11:13Z",
            "title": "PWGLF: fix typos in Nsigma implementation",
            "number": 5317,
            "author": {
              "login": "ddobrigk"
            },
            "files": {
              "edges": [
                {
                  "node": {
                    "path": "PWGLF/TableProducer/lambdakzeropid.cxx"
                  }
                }
              ]
            }
          }
        },
        {
          "node": {
            "state": "MERGED",
            "mergedAt": "2024-03-23T13:57:37Z",
            "title": "PWGMM splitting mcdata for testing",
            "number": 5318,
            "author": {
              "login": "hhesouno"
            },
            "files": {
              "edges": [
                {
                  "node": {
                    "path": "PWGMM/Mult/Tasks/CMakeLists.txt"
                  }
                },
                {
                  "node": {
                    "path": "PWGMM/Mult/Tasks/mcdata_split_test.cxx"
                  }
                }
              ]
            }
          }
        },
        {
          "node": {
            "state": "MERGED",
            "mergedAt": "2024-03-23T19:29:08Z",
            "title": "Update RobustFluctuationObservables.cxx: optimized + new QA",
            "number": 5319,
            "author": {
              "login": "altsybee"
            },
            "files": {
              "edges": [
                {
                  "node": {
                    "path": "PWGCF/EbyEFluctuations/Tasks/RobustFluctuationObservables.cxx"
                  }
                }
              ]
            }
          }
        },
        {
          "node": {
            "state": "MERGED",
            "mergedAt": "2024-03-23T17:10:32Z",
            "title": "kstar flow",
            "number": 5320,
            "author": {
              "login": "sarjeetagami"
            },
            "files": {
              "edges": [
                {
                  "node": {
                    "path": "PWGLF/Tasks/Resonances/CMakeLists.txt"
                  }
                },
                {
                  "node": {
                    "path": "PWGLF/Tasks/Resonances/kstarpbpb.cxx"
                  }
                }
              ]
            }
          }
        },
        {
          "node": {
            "state": "MERGED",
            "mergedAt": "2024-03-23T15:42:37Z",
            "title": "Added histos for ITS-ROF border cut studies + clean up",
            "number": 5321,
            "author": {
              "login": "ekryshen"
            },
            "files": {
              "edges": [
                {
                  "node": {
                    "path": "DPG/Tasks/AOTEvent/eventSelectionQa.cxx"
                  }
                }
              ]
            }
          }
        },
        {
          "node": {
            "state": "MERGED",
            "mergedAt": "2024-03-23T16:57:54Z",
            "title": "Fix for local BC",
            "number": 5322,
            "author": {
              "login": "ekryshen"
            },
            "files": {
              "edges": [
                {
                  "node": {
                    "path": "DPG/Tasks/AOTEvent/eventSelectionQa.cxx"
                  }
                }
              ]
            }
          }
        },
        {
          "node": {
            "state": "MERGED",
            "mergedAt": "2024-03-23T17:40:10Z",
            "title": "Update Resonance PDG codes",
            "number": 5323,
            "author": {
              "login": "BongHwi"
            },
            "files": {
              "edges": [
                {
                  "node": {
                    "path": "PWGLF/TableProducer/LFResonanceInitializer.cxx"
                  }
                }
              ]
            }
          }
        },
        {
          "node": {
            "state": "MERGED",
            "mergedAt": "2024-03-23T19:25:57Z",
            "title": "Revert \"PWGCF: FemtoUniverse -- Add mixing in centrality, PID fix",
            "number": 5324,
            "author": {
              "login": "prchakra"
            },
            "files": {
              "edges": [
                {
                  "node": {
                    "path": "PWGCF/FemtoUniverse/Tasks/femtoUniversePairTaskTrackTrack3DMultKtExtended.cxx"
                  }
                }
              ]
            }
          }
        },
        {
          "node": {
            "state": "MERGED",
            "mergedAt": "2024-03-23T20:38:41Z",
            "title": "Reduce the number of needed histograms",
            "number": 5325,
            "author": {
              "login": "victor-gonzalez"
            },
            "files": {
              "edges": [
                {
                  "node": {
                    "path": "PWGCF/TableProducer/dptdptfilter.h"
                  }
                },
                {
                  "node": {
                    "path": "PWGCF/TwoParticleCorrelations/Tasks/efficiencyAndQc.cxx"
                  }
                }
              ]
            }
          }
        },
        {
          "node": {
            "state": "MERGED",
            "mergedAt": "2024-03-24T08:08:48Z",
            "title": "Adjust cuts and axis limits",
            "number": 5326,
            "author": {
              "login": "ekryshen"
            },
            "files": {
              "edges": [
                {
                  "node": {
                    "path": "DPG/Tasks/AOTEvent/eventSelectionQa.cxx"
                  }
                }
              ]
            }
          }
        },
        {
          "node": {
            "state": "MERGED",
            "mergedAt": "2024-03-24T20:31:26Z",
            "title": "PWGLF: Add Nsigma-TOF @analysis + extra 'findable' debugging",
            "number": 5327,
            "author": {
              "login": "ddobrigk"
            },
            "files": {
              "edges": [
                {
                  "node": {
                    "path": "PWGLF/DataModel/LFStrangenessTables.h"
                  }
                },
                {
                  "node": {
                    "path": "PWGLF/TableProducer/cascademcfinder.cxx"
                  }
                },
                {
                  "node": {
                    "path": "PWGLF/TableProducer/lambdakzeromcfinder.cxx"
                  }
                },
                {
                  "node": {
                    "path": "PWGLF/TableProducer/lambdakzeropid.cxx"
                  }
                },
                {
                  "node": {
                    "path": "PWGLF/Tasks/Strangeness/derivedlambdakzeroanalysis.cxx"
                  }
                }
              ]
            }
          }
        },
        {
          "node": {
            "state": "MERGED",
            "mergedAt": "2024-03-24T13:16:40Z",
            "title": "PWGMM: Mult: Update ReducedTables.h",
            "number": 5328,
            "author": {
              "login": "aalkin"
            },
            "files": {
              "edges": [
                {
                  "node": {
                    "path": "PWGMM/Mult/DataModel/ReducedTables.h"
                  }
                }
              ]
            }
          }
        },
        {
          "node": {
            "state": "MERGED",
            "mergedAt": "2024-03-24T13:42:27Z",
            "title": "Phiv2 sa momentumcutfix",
            "number": 5329,
            "author": {
              "login": "skundu692"
            },
            "files": {
              "edges": [
                {
                  "node": {
                    "path": "PWGLF/Tasks/Resonances/phipbpb.cxx"
                  }
                }
              ]
            }
          }
        },
        {
          "node": {
            "state": "MERGED",
            "mergedAt": "2024-03-25T08:41:05Z",
            "title": "fixed DCA templates and updated param for reweighting of antip",
            "number": 5330,
            "author": {
              "login": "alcaliva"
            },
            "files": {
              "edges": [
                {
                  "node": {
                    "path": "PWGLF/Tasks/Nuspex/nuclei_in_jets.cxx"
                  }
                }
              ]
            }
          }
        },
        {
          "node": {
            "state": "MERGED",
            "mergedAt": "2024-03-24T18:21:40Z",
            "title": "Adde cut on FT0 and collision vertex correlation",
            "number": 5331,
            "author": {
              "login": "ekryshen"
            },
            "files": {
              "edges": [
                {
                  "node": {
                    "path": "DPG/Tasks/AOTEvent/eventSelectionQa.cxx"
                  }
                }
              ]
            }
          }
        },
        {
          "node": {
            "state": "MERGED",
            "mergedAt": "2024-03-24T18:51:59Z",
            "title": "PWGJE: Adding Lc derived jets to framework",
            "number": 5332,
            "author": {
              "login": "nzardosh"
            },
            "files": {
              "edges": [
                {
                  "node": {
                    "path": "PWGHF/DataModel/DerivedTables.h"
                  }
                },
                {
                  "node": {
                    "path": "PWGJE/Core/JetHFUtilities.h"
                  }
                },
                {
                  "node": {
                    "path": "PWGJE/DataModel/Jet.h"
                  }
                },
                {
                  "node": {
                    "path": "PWGJE/DataModel/JetReducedDataHF.h"
                  }
                },
                {
                  "node": {
                    "path": "PWGJE/DataModel/JetSubstructure.h"
                  }
                },
                {
                  "node": {
                    "path": "PWGJE/DataModel/JetSubtraction.h"
                  }
                },
                {
                  "node": {
                    "path": "PWGJE/JetFinders/CMakeLists.txt"
                  }
                },
                {
                  "node": {
                    "path": "PWGJE/JetFinders/jetfinderLcdatacharged.cxx"
                  }
                },
                {
                  "node": {
                    "path": "PWGJE/JetFinders/jetfinderLcmcdcharged.cxx"
                  }
                },
                {
                  "node": {
                    "path": "PWGJE/JetFinders/jetfinderLcmcpcharged.cxx"
                  }
                },
                {
                  "node": {
                    "path": "PWGJE/JetFinders/jetfinderhf.cxx"
                  }
                },
                {
                  "node": {
                    "path": "PWGJE/TableProducer/CMakeLists.txt"
                  }
                },
                {
                  "node": {
                    "path": "PWGJE/TableProducer/jetderiveddataproducer.cxx"
                  }
                },
                {
                  "node": {
                    "path": "PWGJE/TableProducer/jetderiveddataproducerdummy.cxx"
                  }
                },
                {
                  "node": {
                    "path": "PWGJE/TableProducer/jetderiveddataproducerdummyd0.cxx"
                  }
                },
                {
                  "node": {
                    "path": "PWGJE/TableProducer/jetderiveddataproducerdummylc.cxx"
                  }
                },
                {
                  "node": {
                    "path": "PWGJE/TableProducer/jetderiveddatawriter.cxx"
                  }
                },
                {
                  "node": {
                    "path": "PWGJE/TableProducer/jetmatchingmc.cxx"
                  }
                },
                {
                  "node": {
                    "path": "PWGJE/TableProducer/jetmatchingmcsub.cxx"
                  }
                },
                {
                  "node": {
                    "path": "PWGJE/TableProducer/jetmatchingsub.cxx"
                  }
                },
                {
                  "node": {
                    "path": "PWGJE/Tasks/jetfinderhfQA.cxx"
                  }
                },
                {
                  "node": {
                    "path": "PWGJE/Tasks/jetsubstructurehf.cxx"
                  }
                },
                {
                  "node": {
                    "path": "PWGJE/Tasks/jetsubstructurehfoutput.cxx"
                  }
                }
              ]
            }
          }
        },
        {
          "node": {
            "state": "MERGED",
            "mergedAt": "2024-03-24T21:31:41Z",
            "title": "Added cut on same bunch pileup",
            "number": 5333,
            "author": {
              "login": "ekryshen"
            },
            "files": {
              "edges": [
                {
                  "node": {
                    "path": "DPG/Tasks/AOTEvent/eventSelectionQa.cxx"
                  }
                }
              ]
            }
          }
        },
        {
          "node": {
            "state": "CLOSED",
            "mergedAt": null,
            "title": "PWGLF: declarative eta window for speed in MC finding",
            "number": 5334,
            "author": {
              "login": "ddobrigk"
            },
            "files": {
              "edges": [
                {
                  "node": {
                    "path": "PWGLF/TableProducer/lambdakzeromcfinder.cxx"
                  }
                }
              ]
            }
          }
        },
        {
          "node": {
            "state": "MERGED",
            "mergedAt": "2024-03-25T07:26:57Z",
            "title": "PWGLF: Added NoITSROFrameBorder sel cut",
            "number": 5335,
            "author": {
              "login": "hkoley"
            },
            "files": {
              "edges": [
                {
                  "node": {
                    "path": "PWGLF/TableProducer/LFResonanceInitializer.cxx"
                  }
                },
                {
                  "node": {
                    "path": "PWGLF/Utils/collisionCuts.h"
                  }
                }
              ]
            }
          }
        },
        {
          "node": {
            "state": "CLOSED",
            "mergedAt": null,
            "title": "added post calibration with centrality, added TPC ncls cuts",
            "number": 5336,
            "author": {
              "login": "ypwangg"
            },
            "files": {
              "edges": [
                {
                  "node": {
                    "path": "PWGDQ/Core/HistogramsLibrary.cxx"
                  }
                },
                {
                  "node": {
                    "path": "PWGDQ/TableProducer/tableMaker.cxx"
                  }
                }
              ]
            }
          }
        },
        {
          "node": {
            "state": "MERGED",
            "mergedAt": "2024-03-25T11:00:38Z",
            "title": "rework on PWGMM/Mult/Tasks:heavy-ion-mult.cxx",
            "number": 5337,
            "author": {
              "login": "abmodak"
            },
            "files": {
              "edges": [
                {
                  "node": {
                    "path": "PWGMM/Mult/Tasks/heavy-ion-mult.cxx"
                  }
                }
              ]
            }
          }
        },
        {
          "node": {
            "state": "MERGED",
            "mergedAt": "2024-03-25T21:37:17Z",
            "title": "PWGHF: Add columns of impact parameter z for daughters of 2-prong and 3-prong candidates",
            "number": 5338,
            "author": {
              "login": "nzardosh"
            },
            "files": {
              "edges": [
                {
                  "node": {
                    "path": "PWGHF/Core/HfMlResponseD0ToKPi.h"
                  }
                },
                {
                  "node": {
                    "path": "PWGHF/Core/HfMlResponseDplusToPiKPi.h"
                  }
                },
                {
                  "node": {
                    "path": "PWGHF/Core/HfMlResponseDsToKKPi.h"
                  }
                },
                {
                  "node": {
                    "path": "PWGHF/Core/HfMlResponseLcToPKPi.h"
                  }
                },
                {
                  "node": {
                    "path": "PWGHF/Core/HfMlResponseXicToPKPi.h"
                  }
                },
                {
                  "node": {
                    "path": "PWGHF/DataModel/CandidateReconstructionTables.h"
                  }
                },
                {
                  "node": {
                    "path": "PWGHF/TableProducer/candidateCreator2Prong.cxx"
                  }
                },
                {
                  "node": {
                    "path": "PWGHF/TableProducer/candidateCreator3Prong.cxx"
                  }
                }
              ]
            }
          }
        },
        {
          "node": {
            "state": "MERGED",
            "mergedAt": "2024-03-25T13:11:02Z",
            "title": "PWGMM: Mult: only use HepMC in reducer if available",
            "number": 5339,
            "author": {
              "login": "aalkin"
            },
            "files": {
              "edges": [
                {
                  "node": {
                    "path": "PWGMM/Mult/TableProducer/reducer.cxx"
                  }
                }
              ]
            }
          }
        },
        {
          "node": {
            "state": "MERGED",
            "mergedAt": "2024-03-25T19:11:45Z",
            "title": "PWGHF: Sync derived D0 collision tables with Lc",
            "number": 5340,
            "author": {
              "login": "vkucera"
            },
            "files": {
              "edges": [
                {
                  "node": {
                    "path": "PWGHF/DataModel/DerivedTables.h"
                  }
                },
                {
                  "node": {
                    "path": "PWGHF/TableProducer/derivedDataCreatorD0ToKPi.cxx"
                  }
                },
                {
                  "node": {
                    "path": "PWGJE/Core/JetHFUtilities.h"
                  }
                }
              ]
            }
          }
        },
        {
          "node": {
            "state": "MERGED",
            "mergedAt": "2024-03-25T14:29:16Z",
            "title": "mc centrality",
            "number": 5341,
            "author": {
              "login": "sarjeetagami"
            },
            "files": {
              "edges": [
                {
                  "node": {
                    "path": "PWGLF/Tasks/Resonances/phianalysisrun3_PbPb.cxx"
                  }
                }
              ]
            }
          }
        },
        {
          "node": {
            "state": "OPEN",
            "mergedAt": null,
            "title": "PWGHF: Adding sliceby in HF flow task",
            "number": 5342,
            "author": {
              "login": "stefanopolitano"
            },
            "files": {
              "edges": [
                {
                  "node": {
                    "path": "PWGHF/D2H/Tasks/taskFlowCharmHadrons.cxx"
                  }
                }
              ]
            }
          }
        },
        {
          "node": {
            "state": "OPEN",
            "mergedAt": null,
            "title": "PWGHF: HFC, Adding new step in candidate efficiency evaluation",
            "number": 5343,
            "author": {
              "login": "scattaru"
            },
            "files": {
              "edges": [
                {
                  "node": {
                    "path": "PWGHF/HFC/TableProducer/correlatorDsHadrons.cxx"
                  }
                }
              ]
            }
          }
        },
        {
          "node": {
            "state": "MERGED",
            "mergedAt": "2024-03-25T16:21:19Z",
            "title": "Ignore PID pre-selections for MC particles in nucleiSpectra",
            "number": 5344,
            "author": {
              "login": "mpuccio"
            },
            "files": {
              "edges": [
                {
                  "node": {
                    "path": "PWGLF/TableProducer/nucleiSpectra.cxx"
                  }
                }
              ]
            }
          }
        },
        {
          "node": {
            "state": "MERGED",
            "mergedAt": "2024-03-26T12:55:31Z",
            "title": "PWGLF: MC finder consistency and optimization work",
            "number": 5345,
            "author": {
              "login": "ddobrigk"
            },
            "files": {
              "edges": [
                {
                  "node": {
                    "path": "PWGLF/TableProducer/lambdakzeromcfinder.cxx"
                  }
                },
                {
                  "node": {
                    "path": "PWGLF/TableProducer/lambdakzeropid.cxx"
                  }
                }
              ]
            }
          }
        },
        {
          "node": {
            "state": "MERGED",
            "mergedAt": "2024-03-25T19:40:35Z",
            "title": "Update spectraTOF.cxx",
            "number": 5346,
            "author": {
              "login": "RD0407"
            },
            "files": {
              "edges": [
                {
                  "node": {
                    "path": "PWGLF/Tasks/Nuspex/spectraTOF.cxx"
                  }
                }
              ]
            }
          }
        },
        {
          "node": {
            "state": "MERGED",
            "mergedAt": "2024-03-25T20:13:09Z",
            "title": "add estimator correlation and TPC pile up cuts for converted data analysis",
            "number": 5347,
            "author": {
              "login": "maciacco"
            },
            "files": {
              "edges": [
                {
                  "node": {
                    "path": "PWGLF/Tasks/Nuspex/antidLambdaEbye.cxx"
                  }
                }
              ]
            }
          }
        },
        {
          "node": {
            "state": "MERGED",
            "mergedAt": "2024-03-27T21:25:05Z",
            "title": "Fix some compilation warnings (and never have them again)",
            "number": 5348,
            "author": {
              "login": "vkucera"
            },
            "files": {
              "edges": [
                {
                  "node": {
                    "path": "Common/TableProducer/qVectorsTable.cxx"
                  }
                },
                {
                  "node": {
                    "path": "Common/Tasks/ft0Qa.cxx"
                  }
                },
                {
                  "node": {
                    "path": "EventFiltering/PWGHF/HFFilter.cxx"
                  }
                },
                {
                  "node": {
                    "path": "EventFiltering/PWGJE/fullJetFilter.cxx"
                  }
                },
                {
                  "node": {
                    "path": "EventFiltering/PWGJE/jetFilter.cxx"
                  }
                },
                {
                  "node": {
                    "path": "EventFiltering/PWGLF/strangenessFilter.cxx"
                  }
                },
                {
                  "node": {
                    "path": "EventFiltering/cefpTask.cxx"
                  }
                },
                {
                  "node": {
                    "path": "PWGCF/EbyEFluctuations/Tasks/IdentifiedMeanPtFluctuations.cxx"
                  }
                },
                {
                  "node": {
                    "path": "PWGCF/Flow/Tasks/FlowPbPbTask.cxx"
                  }
                },
                {
                  "node": {
                    "path": "PWGCF/GenericFramework/Core/BootstrapProfile.cxx"
                  }
                },
                {
                  "node": {
                    "path": "PWGCF/GenericFramework/Core/FlowPtContainer.cxx"
                  }
                },
                {
                  "node": {
                    "path": "PWGCF/MultiparticleCorrelations/Core/MuPa-MemberFunctions.h"
                  }
                },
                {
                  "node": {
                    "path": "PWGDQ/Core/HistogramsLibrary.cxx"
                  }
                },
                {
                  "node": {
                    "path": "PWGDQ/TableProducer/tableMaker.cxx"
                  }
                },
                {
                  "node": {
                    "path": "PWGDQ/Tasks/dqCorrelation.cxx"
                  }
                },
                {
                  "node": {
                    "path": "PWGDQ/Tasks/filterPPwithAssociation.cxx"
                  }
                },
                {
                  "node": {
                    "path": "PWGEM/Dilepton/Tasks/MCtemplates.cxx"
                  }
                },
                {
                  "node": {
                    "path": "PWGEM/Dilepton/Tasks/emEfficiencyEE.cxx"
                  }
                },
                {
                  "node": {
                    "path": "PWGEM/Tasks/phosNbar.cxx"
                  }
                },
                {
                  "node": {
                    "path": "PWGHF/ALICE3/TableProducer/treeCreatorChicToJpsiGamma.cxx"
                  }
                },
                {
                  "node": {
                    "path": "PWGHF/ALICE3/TableProducer/treeCreatorXToJpsiPiPi.cxx"
                  }
                },
                {
                  "node": {
                    "path": "PWGHF/HFC/TableProducer/correlatorDsHadrons.cxx"
                  }
                },
                {
                  "node": {
                    "path": "PWGHF/Tasks/taskMcEfficiency.cxx"
                  }
                },
                {
                  "node": {
                    "path": "PWGHF/Tasks/taskMcEfficiencyToXiPi.cxx"
                  }
                },
                {
                  "node": {
                    "path": "PWGJE/Tasks/emcvertexselectionqa.cxx"
                  }
                },
                {
                  "node": {
                    "path": "PWGLF/TableProducer/LFResonanceInitializer.cxx"
                  }
                },
                {
                  "node": {
                    "path": "PWGLF/TableProducer/LFStrangeTreeCreator.cxx"
                  }
                },
                {
                  "node": {
                    "path": "PWGLF/TableProducer/epvector.cxx"
                  }
                },
                {
                  "node": {
                    "path": "PWGLF/TableProducer/hyhe4builder.cxx"
                  }
                },
                {
                  "node": {
                    "path": "PWGLF/TableProducer/lithium4analysis.cxx"
                  }
                },
                {
                  "node": {
                    "path": "PWGLF/TableProducer/threebodyRecoTask.cxx"
                  }
                },
                {
                  "node": {
                    "path": "PWGLF/Tasks/Nuspex/hypertriton3bodyMCQA.cxx"
                  }
                },
                {
                  "node": {
                    "path": "PWGLF/Tasks/Resonances/chargedkstaranalysis.cxx"
                  }
                },
                {
                  "node": {
                    "path": "PWGLF/Tasks/Resonances/f0980analysis.cxx"
                  }
                },
                {
                  "node": {
                    "path": "PWGLF/Tasks/Resonances/lambda1520analysis.cxx"
                  }
                },
                {
                  "node": {
                    "path": "PWGMM/Lumi/Tasks/LumiFDDFT0.cxx"
                  }
                },
                {
                  "node": {
                    "path": "PWGMM/Lumi/Tasks/lumi.cxx"
                  }
                },
                {
                  "node": {
                    "path": "PWGMM/Mult/TableProducer/trackPropagation.cxx"
                  }
                },
                {
                  "node": {
                    "path": "PWGMM/Mult/Tasks/dndeta-hi.cxx"
                  }
                },
                {
                  "node": {
                    "path": "PWGMM/Mult/Tasks/vertexing-fwd.cxx"
                  }
                },
                {
                  "node": {
                    "path": "PWGUD/AQC/udQCmidRap.cxx"
                  }
                },
                {
                  "node": {
                    "path": "PWGUD/TableProducer/DGBCCandProducer.cxx"
                  }
                },
                {
                  "node": {
                    "path": "dependencies/O2PhysicsCompileFlags.cmake"
                  }
                }
              ]
            }
          }
        },
        {
          "node": {
            "state": "MERGED",
            "mergedAt": "2024-03-25T20:39:51Z",
            "title": "VtxZ precision vs T0M mult, nContrib vs bc",
            "number": 5349,
            "author": {
              "login": "ekryshen"
            },
            "files": {
              "edges": [
                {
                  "node": {
                    "path": "DPG/Tasks/AOTEvent/eventSelectionQa.cxx"
                  }
                }
              ]
            }
          }
        },
        {
          "node": {
            "state": "MERGED",
            "mergedAt": "2024-03-25T23:28:26Z",
            "title": "[PWGLF] LightNucleiTask - Fix event selection bug",
            "number": 5350,
            "author": {
              "login": "giovannimalfattore"
            },
            "files": {
              "edges": [
                {
                  "node": {
                    "path": "PWGLF/Tasks/Nuspex/LFNucleiBATask.cxx"
                  }
                }
              ]
            }
          }
        },
        {
          "node": {
            "state": "MERGED",
            "mergedAt": "2024-03-25T21:36:52Z",
            "title": "PWGJE: fixing bug with cluster sequence in Nsubjettiness task",
            "number": 5351,
            "author": {
              "login": "nzardosh"
            },
            "files": {
              "edges": [
                {
                  "node": {
                    "path": "PWGJE/Tasks/nSubjettiness.cxx"
                  }
                }
              ]
            }
          }
        },
        {
          "node": {
            "state": "MERGED",
            "mergedAt": "2024-03-26T00:28:09Z",
            "title": "added centrality in MC and corrected bugs in like-sign method and the…",
            "number": 5352,
            "author": {
              "login": "sawankumawat"
            },
            "files": {
              "edges": [
                {
                  "node": {
                    "path": "PWGLF/DataModel/LFResonanceTables.h"
                  }
                },
                {
                  "node": {
                    "path": "PWGLF/TableProducer/LFResonanceInitializer.cxx"
                  }
                },
                {
                  "node": {
                    "path": "PWGLF/Tasks/Resonances/k892analysis.cxx"
                  }
                }
              ]
            }
          }
        },
        {
          "node": {
            "state": "CLOSED",
            "mergedAt": null,
            "title": "PWGHF: fix issue in D0 partition table in charm flow task",
            "number": 5353,
            "author": {
              "login": "Mingyu3360715"
            },
            "files": {
              "edges": [
                {
                  "node": {
                    "path": "PWGHF/D2H/Tasks/taskFlowCharmHadrons.cxx"
                  }
                }
              ]
            }
          }
        },
        {
          "node": {
            "state": "MERGED",
            "mergedAt": "2024-03-26T07:35:34Z",
            "title": "Update deutRtTask.cxx",
            "number": 5354,
            "author": {
              "login": "RD0407"
            },
            "files": {
              "edges": [
                {
                  "node": {
                    "path": "PWGLF/Tasks/Nuspex/deutRtTask.cxx"
                  }
                }
              ]
            }
          }
        },
        {
          "node": {
            "state": "MERGED",
            "mergedAt": "2024-03-26T08:30:01Z",
            "title": "Remove unused ccdb options and simplify Bz field retrieval",
            "number": 5355,
            "author": {
              "login": "mpuccio"
            },
            "files": {
              "edges": [
                {
                  "node": {
                    "path": "PWGLF/TableProducer/nucleiSpectra.cxx"
                  }
                }
              ]
            }
          }
        },
        {
          "node": {
            "state": "CLOSED",
            "mergedAt": null,
            "title": "(PWGCF) SPC Analysis and NUA creation Run3 tasks ",
            "number": 5356,
            "author": {
              "login": "MaximVirta"
            },
            "files": {
              "edges": [
                {
                  "node": {
                    "path": "PWGCF/Flow/Core/CMakeLists.txt"
                  }
                },
                {
                  "node": {
                    "path": "PWGCF/Flow/Core/FlowJHistManager.cxx"
                  }
                },
                {
                  "node": {
                    "path": "PWGCF/Flow/Core/FlowJHistManager.h"
                  }
                },
                {
                  "node": {
                    "path": "PWGCF/Flow/Core/FlowJSPCAnalysis.cxx"
                  }
                },
                {
                  "node": {
                    "path": "PWGCF/Flow/Core/FlowJSPCAnalysis.h"
                  }
                },
                {
                  "node": {
                    "path": "PWGCF/Flow/Core/FlowJSPCObservables.h"
                  }
                },
                {
                  "node": {
                    "path": "PWGCF/Flow/Core/PWGCFFlowLinkDef.h"
                  }
                },
                {
                  "node": {
                    "path": "PWGCF/Flow/Tasks/CMakeLists.txt"
                  }
                },
                {
                  "node": {
                    "path": "PWGCF/Flow/Tasks/flowJNUACreationTask.cxx"
                  }
                },
                {
                  "node": {
                    "path": "PWGCF/Flow/Tasks/flowJSPCAnalysisTask.cxx"
                  }
                }
              ]
            }
          }
        },
        {
          "node": {
            "state": "CLOSED",
            "mergedAt": null,
            "title": " (PWGCF) SPC Analysis and NUA creation Run3 tasks ",
            "number": 5357,
            "author": {
              "login": "MaximVirta"
            },
            "files": {
              "edges": [
                {
                  "node": {
                    "path": "PWGCF/Flow/Core/CMakeLists.txt"
                  }
                },
                {
                  "node": {
                    "path": "PWGCF/Flow/Core/FlowJHistManager.cxx"
                  }
                },
                {
                  "node": {
                    "path": "PWGCF/Flow/Core/FlowJHistManager.h"
                  }
                },
                {
                  "node": {
                    "path": "PWGCF/Flow/Core/FlowJSPCAnalysis.cxx"
                  }
                },
                {
                  "node": {
                    "path": "PWGCF/Flow/Core/FlowJSPCAnalysis.h"
                  }
                },
                {
                  "node": {
                    "path": "PWGCF/Flow/Core/FlowJSPCObservables.h"
                  }
                },
                {
                  "node": {
                    "path": "PWGCF/Flow/Core/PWGCFFlowLinkDef.h"
                  }
                },
                {
                  "node": {
                    "path": "PWGCF/Flow/Tasks/CMakeLists.txt"
                  }
                },
                {
                  "node": {
                    "path": "PWGCF/Flow/Tasks/flowJNUACreationTask.cxx"
                  }
                },
                {
                  "node": {
                    "path": "PWGCF/Flow/Tasks/flowJSPCAnalysisTask.cxx"
                  }
                }
              ]
            }
          }
        },
        {
          "node": {
            "state": "CLOSED",
            "mergedAt": null,
            "title": " (PWGCF) SPC Analysis and NUA creation Run3 tasks",
            "number": 5358,
            "author": {
              "login": "MaximVirta"
            },
            "files": {
              "edges": [
                {
                  "node": {
                    "path": "PWGCF/Flow/Core/CMakeLists.txt"
                  }
                },
                {
                  "node": {
                    "path": "PWGCF/Flow/Core/FlowJHistManager.cxx"
                  }
                },
                {
                  "node": {
                    "path": "PWGCF/Flow/Core/FlowJHistManager.h"
                  }
                },
                {
                  "node": {
                    "path": "PWGCF/Flow/Core/FlowJSPCAnalysis.cxx"
                  }
                },
                {
                  "node": {
                    "path": "PWGCF/Flow/Core/FlowJSPCAnalysis.h"
                  }
                },
                {
                  "node": {
                    "path": "PWGCF/Flow/Core/FlowJSPCObservables.h"
                  }
                },
                {
                  "node": {
                    "path": "PWGCF/Flow/Core/PWGCFFlowLinkDef.h"
                  }
                },
                {
                  "node": {
                    "path": "PWGCF/Flow/Tasks/CMakeLists.txt"
                  }
                },
                {
                  "node": {
                    "path": "PWGCF/Flow/Tasks/flowJNUACreationTask.cxx"
                  }
                },
                {
                  "node": {
                    "path": "PWGCF/Flow/Tasks/flowJSPCAnalysisTask.cxx"
                  }
                }
              ]
            }
          }
        },
        {
          "node": {
            "state": "CLOSED",
            "mergedAt": null,
            "title": " (PWGCF) SPC Analysis and NUA creation Run3 tasks",
            "number": 5359,
            "author": {
              "login": "MaximVirta"
            },
            "files": {
              "edges": [
                {
                  "node": {
                    "path": "PWGCF/Flow/Core/CMakeLists.txt"
                  }
                },
                {
                  "node": {
                    "path": "PWGCF/Flow/Core/FlowJHistManager.cxx"
                  }
                },
                {
                  "node": {
                    "path": "PWGCF/Flow/Core/FlowJHistManager.h"
                  }
                },
                {
                  "node": {
                    "path": "PWGCF/Flow/Core/FlowJSPCAnalysis.cxx"
                  }
                },
                {
                  "node": {
                    "path": "PWGCF/Flow/Core/FlowJSPCAnalysis.h"
                  }
                },
                {
                  "node": {
                    "path": "PWGCF/Flow/Core/FlowJSPCObservables.h"
                  }
                },
                {
                  "node": {
                    "path": "PWGCF/Flow/Core/PWGCFFlowLinkDef.h"
                  }
                },
                {
                  "node": {
                    "path": "PWGCF/Flow/Tasks/CMakeLists.txt"
                  }
                },
                {
                  "node": {
                    "path": "PWGCF/Flow/Tasks/flowJNUACreationTask.cxx"
                  }
                },
                {
                  "node": {
                    "path": "PWGCF/Flow/Tasks/flowJSPCAnalysisTask.cxx"
                  }
                }
              ]
            }
          }
        },
        {
          "node": {
            "state": "CLOSED",
            "mergedAt": null,
            "title": "(PWGCF) SPC Analysis and NUA creation Run3 tasks",
            "number": 5360,
            "author": {
              "login": "MaximVirta"
            },
            "files": {
              "edges": []
            }
          }
        },
        {
          "node": {
            "state": "CLOSED",
            "mergedAt": null,
            "title": "(PWGCF) Initial push for SPC and NUA creation Run3 tasks",
            "number": 5361,
            "author": {
              "login": "MaximVirta"
            },
            "files": {
              "edges": [
                {
                  "node": {
                    "path": "PWGCF/Flow/Core/CMakeLists.txt"
                  }
                },
                {
                  "node": {
                    "path": "PWGCF/Flow/Core/FlowJHistManager.cxx"
                  }
                },
                {
                  "node": {
                    "path": "PWGCF/Flow/Core/FlowJHistManager.h"
                  }
                },
                {
                  "node": {
                    "path": "PWGCF/Flow/Core/FlowJSPCAnalysis.cxx"
                  }
                },
                {
                  "node": {
                    "path": "PWGCF/Flow/Core/FlowJSPCAnalysis.h"
                  }
                },
                {
                  "node": {
                    "path": "PWGCF/Flow/Core/FlowJSPCObservables.h"
                  }
                },
                {
                  "node": {
                    "path": "PWGCF/Flow/Core/PWGCFFlowLinkDef.h"
                  }
                },
                {
                  "node": {
                    "path": "PWGCF/Flow/Tasks/CMakeLists.txt"
                  }
                },
                {
                  "node": {
                    "path": "PWGCF/Flow/Tasks/flowJNUACreationTask.cxx"
                  }
                },
                {
                  "node": {
                    "path": "PWGCF/Flow/Tasks/flowJSPCAnalysisTask.cxx"
                  }
                }
              ]
            }
          }
        },
        {
          "node": {
            "state": "MERGED",
            "mergedAt": "2024-03-27T14:42:59Z",
            "title": "[PWGDQ] Add global configuration for tracking parameters used in record task",
            "number": 5362,
            "author": {
              "login": "Elros60"
            },
            "files": {
              "edges": [
                {
                  "node": {
                    "path": "PWGDQ/Tasks/mchAlignRecord.cxx"
                  }
                }
              ]
            }
          }
        },
        {
          "node": {
            "state": "MERGED",
            "mergedAt": "2024-03-26T16:03:56Z",
            "title": "Add TOF information",
            "number": 5363,
            "author": {
              "login": "fmazzasc"
            },
            "files": {
              "edges": [
                {
                  "node": {
                    "path": "PWGLF/TableProducer/hyperKinkRecoTask.cxx"
                  }
                }
              ]
            }
          }
        },
        {
          "node": {
            "state": "MERGED",
            "mergedAt": "2024-03-26T13:29:16Z",
            "title": "Bug fix",
            "number": 5364,
            "author": {
              "login": "ekryshen"
            },
            "files": {
              "edges": [
                {
                  "node": {
                    "path": "DPG/Tasks/AOTEvent/eventSelectionQa.cxx"
                  }
                }
              ]
            }
          }
        },
        {
          "node": {
            "state": "CLOSED",
            "mergedAt": null,
            "title": "(PWGCF) Initial push for SPC and NUA creation Run3 tasks",
            "number": 5365,
            "author": {
              "login": "MaximVirta"
            },
            "files": {
              "edges": [
                {
                  "node": {
                    "path": "PWGCF/Flow/Core/CMakeLists.txt"
                  }
                },
                {
                  "node": {
                    "path": "PWGCF/Flow/Core/FlowJHistManager.cxx"
                  }
                },
                {
                  "node": {
                    "path": "PWGCF/Flow/Core/FlowJHistManager.h"
                  }
                },
                {
                  "node": {
                    "path": "PWGCF/Flow/Core/FlowJSPCAnalysis.cxx"
                  }
                },
                {
                  "node": {
                    "path": "PWGCF/Flow/Core/FlowJSPCAnalysis.h"
                  }
                },
                {
                  "node": {
                    "path": "PWGCF/Flow/Core/FlowJSPCObservables.h"
                  }
                },
                {
                  "node": {
                    "path": "PWGCF/Flow/Core/PWGCFFlowLinkDef.h"
                  }
                },
                {
                  "node": {
                    "path": "PWGCF/Flow/Tasks/CMakeLists.txt"
                  }
                },
                {
                  "node": {
                    "path": "PWGCF/Flow/Tasks/flowJNUACreationTask.cxx"
                  }
                },
                {
                  "node": {
                    "path": "PWGCF/Flow/Tasks/flowJSPCAnalysisTask.cxx"
                  }
                }
              ]
            }
          }
        },
        {
          "node": {
            "state": "OPEN",
            "mergedAt": null,
            "title": "(PWGCF) Initial push for SPC and NUA creation Run3 tasks",
            "number": 5366,
            "author": {
              "login": "MaximVirta"
            },
            "files": {
              "edges": [
                {
                  "node": {
                    "path": "PWGCF/Flow/Core/CMakeLists.txt"
                  }
                },
                {
                  "node": {
                    "path": "PWGCF/Flow/Core/FlowJHistManager.cxx"
                  }
                },
                {
                  "node": {
                    "path": "PWGCF/Flow/Core/FlowJHistManager.h"
                  }
                },
                {
                  "node": {
                    "path": "PWGCF/Flow/Core/FlowJSPCAnalysis.cxx"
                  }
                },
                {
                  "node": {
                    "path": "PWGCF/Flow/Core/FlowJSPCAnalysis.h"
                  }
                },
                {
                  "node": {
                    "path": "PWGCF/Flow/Core/FlowJSPCObservables.h"
                  }
                },
                {
                  "node": {
                    "path": "PWGCF/Flow/Core/PWGCFFlowLinkDef.h"
                  }
                },
                {
                  "node": {
                    "path": "PWGCF/Flow/Tasks/CMakeLists.txt"
                  }
                },
                {
                  "node": {
                    "path": "PWGCF/Flow/Tasks/flowJNUACreationTask.cxx"
                  }
                },
                {
                  "node": {
                    "path": "PWGCF/Flow/Tasks/flowJSPCAnalysisTask.cxx"
                  }
                }
              ]
            }
          }
        },
        {
          "node": {
            "state": "MERGED",
            "mergedAt": "2024-03-27T14:42:41Z",
            "title": "[PWGDQ] Add extra QA histograms of Q-vectors for cross-component check with acceptance correction",
            "number": 5367,
            "author": {
              "login": "Elros60"
            },
            "files": {
              "edges": [
                {
                  "node": {
                    "path": "PWGDQ/Core/HistogramsLibrary.cxx"
                  }
                }
              ]
            }
          }
        },
        {
          "node": {
            "state": "MERGED",
            "mergedAt": "2024-03-26T14:57:01Z",
            "title": "PWGMM: Mult: dndeta: add centrality-binned track efficiency",
            "number": 5368,
            "author": {
              "login": "aalkin"
            },
            "files": {
              "edges": [
                {
                  "node": {
                    "path": "PWGMM/Mult/Tasks/dndeta.cxx"
                  }
                }
              ]
            }
          }
        },
        {
          "node": {
            "state": "MERGED",
            "mergedAt": "2024-03-27T07:59:37Z",
            "title": "PWGLF: deal with TPC-only duplicates in findable exercise",
            "number": 5369,
            "author": {
              "login": "ddobrigk"
            },
            "files": {
              "edges": [
                {
                  "node": {
                    "path": "PWGLF/TableProducer/lambdakzeromcfinder.cxx"
                  }
                }
              ]
            }
          }
        },
        {
          "node": {
            "state": "MERGED",
            "mergedAt": "2024-03-27T07:03:10Z",
            "title": "updated reweighting and fixed bug",
            "number": 5370,
            "author": {
              "login": "alcaliva"
            },
            "files": {
              "edges": [
                {
                  "node": {
                    "path": "PWGLF/Tasks/Nuspex/nuclei_in_jets.cxx"
                  }
                }
              ]
            }
          }
        },
        {
          "node": {
            "state": "MERGED",
            "mergedAt": "2024-03-27T13:51:24Z",
            "title": "Compute absorption information for nuclei",
            "number": 5371,
            "author": {
              "login": "fmazzasc"
            },
            "files": {
              "edges": [
                {
                  "node": {
                    "path": "PWGLF/DataModel/LFSlimNucleiTables.h"
                  }
                },
                {
                  "node": {
                    "path": "PWGLF/TableProducer/nucleiSpectra.cxx"
                  }
                }
              ]
            }
          }
        },
        {
          "node": {
            "state": "MERGED",
            "mergedAt": "2024-03-27T13:21:16Z",
            "title": "PWGHF: Add the availability for type3 and type 4 muon tracks in HFL muon source task",
            "number": 5372,
            "author": {
              "login": "MaolinZH"
            },
            "files": {
              "edges": [
                {
                  "node": {
                    "path": "PWGHF/HFL/Tasks/taskSingleMuonSource.cxx"
                  }
                }
              ]
            }
          }
        },
        {
          "node": {
            "state": "MERGED",
            "mergedAt": "2024-03-27T08:55:50Z",
            "title": "PWGEM+JE: Add validated/true cluster and pi0 workflow for EMC",
            "number": 5373,
            "author": {
              "login": "nstrangm"
            },
            "files": {
              "edges": [
                {
                  "node": {
                    "path": "PWGEM/PhotonMeson/DataModel/gammaTables.h"
                  }
                },
                {
                  "node": {
                    "path": "PWGEM/PhotonMeson/TableProducer/associateMCinfo.cxx"
                  }
                },
                {
                  "node": {
                    "path": "PWGEM/PhotonMeson/TableProducer/skimmerGammaCalo.cxx"
                  }
                },
                {
                  "node": {
                    "path": "PWGEM/PhotonMeson/Tasks/Pi0EtaToGammaGammaMC.cxx"
                  }
                },
                {
                  "node": {
                    "path": "PWGJE/TableProducer/emcalCorrectionTask.cxx"
                  }
                }
              ]
            }
          }
        },
        {
          "node": {
            "state": "MERGED",
            "mergedAt": "2024-03-27T16:26:27Z",
            "title": "EventFiltering : Adding D0 and Lc tagged jet triggers",
            "number": 5374,
            "author": {
              "login": "nzardosh"
            },
            "files": {
              "edges": [
                {
                  "node": {
                    "path": "EventFiltering/CMakeLists.txt"
                  }
                },
                {
                  "node": {
                    "path": "EventFiltering/PWGJE/jetHFFilter.cxx"
                  }
                },
                {
                  "node": {
                    "path": "EventFiltering/filterTables.h"
                  }
                },
                {
                  "node": {
                    "path": "PWGJE/Core/JetDerivedDataUtilities.h"
                  }
                },
                {
                  "node": {
                    "path": "PWGJE/DataModel/JetReducedData.h"
                  }
                },
                {
                  "node": {
                    "path": "PWGJE/TableProducer/jetderiveddatatriggerproducer.cxx"
                  }
                },
                {
                  "node": {
                    "path": "PWGJE/TableProducer/jetderiveddatawriter.cxx"
                  }
                },
                {
                  "node": {
                    "path": "PWGJE/Tasks/jetfinderhfQA.cxx"
                  }
                }
              ]
            }
          }
        },
        {
          "node": {
            "state": "MERGED",
            "mergedAt": "2024-03-26T21:24:41Z",
            "title": "Phi sa26032024",
            "number": 5375,
            "author": {
              "login": "skundu692"
            },
            "files": {
              "edges": [
                {
                  "node": {
                    "path": "PWGLF/Tasks/Resonances/phipbpb.cxx"
                  }
                }
              ]
            }
          }
        },
        {
          "node": {
            "state": "MERGED",
            "mergedAt": "2024-03-26T20:53:48Z",
            "title": "PWGJE: Fixing missing process switch in derived data producer for D0 MC",
            "number": 5376,
            "author": {
              "login": "nzardosh"
            },
            "files": {
              "edges": [
                {
                  "node": {
                    "path": "PWGJE/TableProducer/jetderiveddataproducer.cxx"
                  }
                }
              ]
            }
          }
        },
        {
          "node": {
            "state": "MERGED",
            "mergedAt": "2024-03-26T20:34:33Z",
            "title": "Use generated pt and rapidity in MC",
            "number": 5377,
            "author": {
              "login": "romainschotter"
            },
            "files": {
              "edges": [
                {
                  "node": {
                    "path": "PWGLF/Tasks/Strangeness/derivedlambdakzeroanalysis.cxx"
                  }
                }
              ]
            }
          }
        },
        {
          "node": {
            "state": "MERGED",
            "mergedAt": "2024-03-27T14:49:14Z",
            "title": "[PWGDQ] Macro for sending GFWWeights to a user-path CCDB",
            "number": 5378,
            "author": {
              "login": "Elros60"
            },
            "files": {
              "edges": [
                {
                  "node": {
                    "path": "PWGDQ/Macros/dqFlowAccWeights.C"
                  }
                }
              ]
            }
          }
        },
        {
          "node": {
            "state": "MERGED",
            "mergedAt": "2024-03-26T19:18:01Z",
            "title": "First version of luminosity QA task",
            "number": 5379,
            "author": {
              "login": "ekryshen"
            },
            "files": {
              "edges": [
                {
                  "node": {
                    "path": "DPG/Tasks/AOTEvent/CMakeLists.txt"
                  }
                },
                {
                  "node": {
                    "path": "DPG/Tasks/AOTEvent/lumiQa.cxx"
                  }
                }
              ]
            }
          }
        },
        {
          "node": {
            "state": "MERGED",
            "mergedAt": "2024-03-26T19:47:26Z",
            "title": "added manual track selection cuts",
            "number": 5380,
            "author": {
              "login": "sawankumawat"
            },
            "files": {
              "edges": [
                {
                  "node": {
                    "path": "PWGLF/DataModel/LFResonanceTables.h"
                  }
                },
                {
                  "node": {
                    "path": "PWGLF/TableProducer/LFResonanceInitializer.cxx"
                  }
                },
                {
                  "node": {
                    "path": "PWGLF/Tasks/Resonances/k892analysis.cxx"
                  }
                }
              ]
            }
          }
        },
        {
          "node": {
            "state": "OPEN",
            "mergedAt": null,
            "title": "PWGHF: Add ML scores in derived D0 and Lc tables",
            "number": 5381,
            "author": {
              "login": "vkucera"
            },
            "files": {
              "edges": [
                {
                  "node": {
                    "path": "PWGHF/DataModel/DerivedTables.h"
                  }
                },
                {
                  "node": {
                    "path": "PWGHF/TableProducer/derivedDataCreatorD0ToKPi.cxx"
                  }
                },
                {
                  "node": {
                    "path": "PWGHF/TableProducer/derivedDataCreatorLcToPKPi.cxx"
                  }
                },
                {
                  "node": {
                    "path": "PWGHF/TableProducer/treeCreatorLcToPKPi.cxx"
                  }
                }
              ]
            }
          }
        },
        {
          "node": {
            "state": "MERGED",
            "mergedAt": "2024-03-27T00:46:26Z",
            "title": "PWGHF: Fix compilation warnings: sign-compare",
            "number": 5382,
            "author": {
              "login": "vkucera"
            },
            "files": {
              "edges": [
                {
                  "node": {
                    "path": "PWGHF/HFC/Tasks/taskCorrelationD0Hadrons.cxx"
                  }
                }
              ]
            }
          }
        },
        {
          "node": {
            "state": "MERGED",
            "mergedAt": "2024-03-27T10:13:27Z",
            "title": "PWGHF: fix loop over generated particles toXiPi",
            "number": 5383,
            "author": {
              "login": "ZFederica"
            },
            "files": {
              "edges": [
                {
                  "node": {
                    "path": "PWGHF/TableProducer/candidateCreatorToXiPi.cxx"
                  }
                }
              ]
            }
          }
        },
        {
          "node": {
            "state": "MERGED",
            "mergedAt": "2024-03-27T17:38:11Z",
            "title": "CF: Update RobustFluctuationObservables.cxx - new QA features + cleanup",
            "number": 5384,
            "author": {
              "login": "altsybee"
            },
            "files": {
              "edges": [
                {
                  "node": {
                    "path": "PWGCF/EbyEFluctuations/Tasks/RobustFluctuationObservables.cxx"
                  }
                }
              ]
            }
          }
        },
        {
          "node": {
            "state": "OPEN",
            "mergedAt": null,
            "title": "PWGHF: implement process function using tracked cascades information toXiPi",
            "number": 5385,
            "author": {
              "login": "ZFederica"
            },
            "files": {
              "edges": [
                {
                  "node": {
                    "path": "PWGHF/TableProducer/candidateCreatorToXiPi.cxx"
                  }
                }
              ]
            }
          }
        },
        {
          "node": {
            "state": "CLOSED",
            "mergedAt": null,
            "title": "[PWGMM] Chnage TH1I to TH1L in trackPropagation.cxx",
            "number": 5386,
            "author": {
              "login": "sarahherrmann"
            },
            "files": {
              "edges": [
                {
                  "node": {
                    "path": "PWGMM/Mult/TableProducer/trackPropagation.cxx"
                  }
                }
              ]
            }
          }
        },
        {
          "node": {
            "state": "MERGED",
            "mergedAt": "2024-03-27T16:55:32Z",
            "title": "PWGLF: PbPb V0 debug + findable study + modularity, optimisations",
            "number": 5387,
            "author": {
              "login": "ddobrigk"
            },
            "files": {
              "edges": [
                {
                  "node": {
                    "path": "PWGLF/Tasks/Strangeness/derivedlambdakzeroanalysis.cxx"
                  }
                }
              ]
            }
          }
        },
        {
          "node": {
            "state": "MERGED",
            "mergedAt": "2024-03-27T13:18:52Z",
            "title": "[PWGMM] Change the type of histograms in trackPropagation.cxx",
            "number": 5388,
            "author": {
              "login": "sarahherrmann"
            },
            "files": {
              "edges": [
                {
                  "node": {
                    "path": "PWGMM/Mult/TableProducer/trackPropagation.cxx"
                  }
                }
              ]
            }
          }
        },
        {
          "node": {
            "state": "MERGED",
            "mergedAt": "2024-03-27T16:57:11Z",
            "title": "PWGCF: fix for event mixing",
            "number": 5389,
            "author": {
              "login": "ariedel-cern"
            },
            "files": {
              "edges": [
                {
                  "node": {
                    "path": "PWGCF/FemtoDream/Tasks/femtoDreamPairTaskTrackTrack.cxx"
                  }
                },
                {
                  "node": {
                    "path": "PWGCF/FemtoDream/Tasks/femtoDreamPairTaskTrackV0.cxx"
                  }
                }
              ]
            }
          }
        },
        {
          "node": {
            "state": "MERGED",
            "mergedAt": "2024-03-27T19:47:15Z",
            "title": "PWGCF:FemtoUniverse - D0/D0bar analysis update",
            "number": 5390,
            "author": {
              "login": "kgwizdzi"
            },
            "files": {
              "edges": [
                {
                  "node": {
                    "path": "PWGCF/FemtoUniverse/TableProducer/femtoUniverseProducerTask.cxx"
                  }
                },
                {
                  "node": {
                    "path": "PWGCF/FemtoUniverse/Tasks/femtoUniversePairTaskTrackD0.cxx"
                  }
                }
              ]
            }
          }
        },
        {
          "node": {
            "state": "MERGED",
            "mergedAt": "2024-03-27T15:52:34Z",
            "title": "PWGMM: Mult: fix histogram dimension",
            "number": 5391,
            "author": {
              "login": "aalkin"
            },
            "files": {
              "edges": [
                {
                  "node": {
                    "path": "PWGMM/Mult/Tasks/dndeta.cxx"
                  }
                }
              ]
            }
          }
        },
        {
          "node": {
            "state": "MERGED",
            "mergedAt": "2024-03-27T17:53:02Z",
            "title": "[event plane] fix",
            "number": 5392,
            "author": {
              "login": "jikim1290"
            },
            "files": {
              "edges": [
                {
                  "node": {
                    "path": "Common/TableProducer/qVectorsTable.cxx"
                  }
                }
              ]
            }
          }
        },
        {
          "node": {
            "state": "MERGED",
            "mergedAt": "2024-03-27T18:18:38Z",
            "title": "Hifixmehisto",
            "number": 5393,
            "author": {
              "login": "skundu692"
            },
            "files": {
              "edges": [
                {
                  "node": {
                    "path": "PWGLF/Tasks/Resonances/phipbpb.cxx"
                  }
                }
              ]
            }
          }
        },
        {
          "node": {
            "state": "MERGED",
            "mergedAt": "2024-03-27T18:48:52Z",
            "title": "adding TimeFrame cut and TPC Ncls fraction cut",
            "number": 5394,
            "author": {
              "login": "glromane"
            },
            "files": {
              "edges": [
                {
                  "node": {
                    "path": "PWGCF/Femto3D/DataModel/singletrackselector.h"
                  }
                },
                {
                  "node": {
                    "path": "PWGCF/Femto3D/TableProducer/singleTrackSelector.cxx"
                  }
                },
                {
                  "node": {
                    "path": "PWGCF/Femto3D/Tasks/femto3dPairTask.cxx"
                  }
                },
                {
                  "node": {
                    "path": "PWGCF/Femto3D/Tasks/femto3dPairTaskMC.cxx"
                  }
                },
                {
                  "node": {
                    "path": "PWGCF/Femto3D/Tasks/femto3dQA.cxx"
                  }
                }
              ]
            }
          }
        },
        {
          "node": {
            "state": "MERGED",
            "mergedAt": "2024-03-27T19:38:34Z",
            "title": "[PWGDQ] Adding flow extra table from central Q-vector framework",
            "number": 5395,
            "author": {
              "login": "lucamicheletti93"
            },
            "files": {
              "edges": [
                {
                  "node": {
                    "path": "PWGDQ/Core/VarManager.h"
                  }
                },
                {
                  "node": {
                    "path": "PWGDQ/DataModel/ReducedInfoTables.h"
                  }
                },
                {
                  "node": {
                    "path": "PWGDQ/Tasks/dqFlow.cxx"
                  }
                },
                {
                  "node": {
                    "path": "PWGDQ/Tasks/tableReader.cxx"
                  }
                }
              ]
            }
          }
        },
        {
          "node": {
            "state": "OPEN",
            "mergedAt": null,
            "title": "Fix iteration on particles",
            "number": 5396,
            "author": {
              "login": "njacazio"
            },
            "files": {
              "edges": [
                {
                  "node": {
                    "path": "PWGLF/Tasks/Nuspex/nuclei_in_jets.cxx"
                  }
                }
              ]
            }
          }
        },
        {
          "node": {
            "state": "MERGED",
            "mergedAt": "2024-03-27T21:10:29Z",
            "title": "MM: particles 2 tracks alternate process test",
            "number": 5397,
            "author": {
              "login": "ddobrigk"
            },
            "files": {
              "edges": [
                {
                  "node": {
                    "path": "PWGMM/Mult/TableProducer/particles2tracks.cxx"
                  }
                }
              ]
            }
          }
        },
        {
          "node": {
            "state": "OPEN",
            "mergedAt": null,
            "title": "PWGCF: Elliptic flow with GFW",
            "number": 5398,
            "author": {
              "login": "ilikmeta"
            },
            "files": {
              "edges": [
                {
                  "node": {
                    "path": "PWGCF/Flow/Tasks/CMakeLists.txt"
                  }
                },
                {
                  "node": {
                    "path": "PWGCF/Flow/Tasks/FlowGFWPbPb.cxx"
                  }
                }
              ]
            }
          }
        }
      ]
    }
  }
}
